{
  "id" : "enviarEmailReuniaoProgresso",
  "name" : "enviarEmailReuniaoProgresso",
  "type" : "form",
  "uuid" : "90d82214-2c2c-4a1f-a8f0-bde0154c7985",
  "modelVersion" : "2.4",
  "lastUpdate" : 1686623135327,
  "description" : "Page generated with Bonita UI designer",
  "rows" : [
    [
      {
        "type" : "container",
        "dimension" : {
          "xs" : 12
        },
        "propertyValues" : { },
        "reference" : "261a13b3-597b-4de3-b5f4-184b5b690b8e",
        "hasValidationError" : false,
        "id" : "pbContainer",
        "rows" : [
          [
            {
              "type" : "component",
              "dimension" : {
                "md" : 12,
                "sm" : 12,
                "xs" : 12,
                "lg" : 12
              },
              "propertyValues" : {
                "hidden" : {
                  "type" : "constant",
                  "value" : false
                },
                "level" : {
                  "type" : "constant",
                  "value" : "Level 1"
                },
                "cssClasses" : {
                  "type" : "constant",
                  "value" : ""
                },
                "text" : {
                  "type" : "interpolation",
                  "value" : "{{ task.displayName }}"
                },
                "alignment" : {
                  "type" : "constant",
                  "value" : "center"
                },
                "dimension" : {
                  "type" : "constant",
                  "value" : 12
                }
              },
              "reference" : "e8d948ca-6ed4-49cb-9a9b-436a7383f4a7",
              "hasValidationError" : false,
              "id" : "pbTitle",
              "description" : ""
            }
          ],
          [
            {
              "type" : "component",
              "dimension" : {
                "md" : 12,
                "sm" : 12,
                "xs" : 12,
                "lg" : 12
              },
              "propertyValues" : {
                "allowHtml" : {
                  "type" : "constant",
                  "value" : true
                },
                "labelHidden" : {
                  "type" : "constant",
                  "value" : true
                },
                "hidden" : {
                  "type" : "constant",
                  "value" : false
                },
                "cssClasses" : {
                  "type" : "constant",
                  "value" : ""
                },
                "label" : {
                  "type" : "interpolation"
                },
                "text" : {
                  "type" : "interpolation",
                  "value" : "{{ task.displayDescription }}"
                },
                "alignment" : {
                  "type" : "constant",
                  "value" : "left"
                },
                "dimension" : {
                  "type" : "constant",
                  "value" : 12
                }
              },
              "reference" : "46357575-fa09-4ad3-b893-00b645a19575",
              "hasValidationError" : false,
              "id" : "pbText",
              "description" : ""
            }
          ]
        ]
      }
    ],
    [
      {
        "type" : "formContainer",
        "dimension" : {
          "xs" : 12
        },
        "propertyValues" : { },
        "reference" : "d757fe41-a35e-4fda-8600-b1bcb2039a50",
        "hasValidationError" : false,
        "id" : "pbFormContainer",
        "container" : {
          "type" : "container",
          "dimension" : {
            "xs" : 12
          },
          "propertyValues" : { },
          "reference" : "72ec775c-287d-4abf-8573-5114557a787d",
          "hasValidationError" : false,
          "id" : "pbContainer",
          "rows" : [
            [
              {
                "type" : "component",
                "dimension" : {
                  "md" : 12,
                  "sm" : 12,
                  "xs" : 12,
                  "lg" : 12
                },
                "propertyValues" : {
                  "labelHidden" : {
                    "type" : "constant",
                    "value" : false
                  },
                  "hidden" : {
                    "type" : "constant",
                    "value" : false
                  },
                  "cssClasses" : {
                    "type" : "constant",
                    "value" : ""
                  },
                  "disabled" : {
                    "type" : "constant",
                    "value" : false
                  },
                  "label" : {
                    "type" : "interpolation",
                    "value" : "É necessário envio de email?"
                  },
                  "dimension" : {
                    "type" : "constant",
                    "value" : 12
                  },
                  "value" : {
                    "type" : "variable",
                    "value" : "formInput.enviarEmail2"
                  },
                  "required" : {
                    "type" : "constant",
                    "value" : false
                  },
                  "allowHTML" : {
                    "type" : "constant",
                    "value" : false
                  }
                },
                "reference" : "6af3d064-0cc7-4d62-9cb9-8dcae261d34e",
                "hasValidationError" : false,
                "id" : "pbCheckbox",
                "description" : ""
              }
            ],
            [
              {
                "type" : "component",
                "dimension" : {
                  "md" : 12,
                  "sm" : 12,
                  "xs" : 12,
                  "lg" : 12
                },
                "propertyValues" : {
                  "removeItem" : {
                    "type" : "variable"
                  },
                  "hidden" : {
                    "type" : "constant",
                    "value" : false
                  },
                  "cssClasses" : {
                    "type" : "constant",
                    "value" : ""
                  },
                  "buttonStyle" : {
                    "type" : "constant",
                    "value" : "primary"
                  },
                  "label" : {
                    "type" : "interpolation",
                    "value" : "Submit"
                  },
                  "dataToSend" : {
                    "type" : "expression",
                    "value" : "formOutput"
                  },
                  "dataFromError" : {
                    "type" : "variable",
                    "value" : "formOutput._submitError"
                  },
                  "allowHTML" : {
                    "type" : "constant",
                    "value" : false
                  },
                  "labelHidden" : {
                    "type" : "constant",
                    "value" : false
                  },
                  "collectionPosition" : {
                    "type" : "constant"
                  },
                  "targetUrlOnSuccess" : {
                    "type" : "interpolation",
                    "value" : "/bonita"
                  },
                  "action" : {
                    "type" : "constant",
                    "value" : "Submit task"
                  },
                  "collectionToModify" : {
                    "type" : "variable"
                  },
                  "valueToAdd" : {
                    "type" : "expression"
                  },
                  "disabled" : {
                    "type" : "expression",
                    "value" : "$form.$invalid"
                  },
                  "alignment" : {
                    "type" : "constant",
                    "value" : "center"
                  },
                  "dimension" : {
                    "type" : "constant",
                    "value" : 12
                  }
                },
                "reference" : "53dad3af-1421-47cc-8730-406f5c534e93",
                "hasValidationError" : false,
                "id" : "pbButton",
                "description" : ""
              }
            ],
            [
              {
                "type" : "component",
                "dimension" : {
                  "md" : 12,
                  "sm" : 12,
                  "xs" : 12,
                  "lg" : 12
                },
                "propertyValues" : {
                  "allowHTML" : {
                    "type" : "constant",
                    "value" : true
                  },
                  "allowHtml" : {
                    "type" : "constant",
                    "value" : true
                  },
                  "labelHidden" : {
                    "type" : "constant",
                    "value" : true
                  },
                  "hidden" : {
                    "type" : "expression",
                    "value" : "!formOutput._submitError.message"
                  },
                  "cssClasses" : {
                    "type" : "constant",
                    "value" : "alert alert-danger col-lg-6 col-lg-offset-3"
                  },
                  "label" : {
                    "type" : "interpolation"
                  },
                  "text" : {
                    "type" : "interpolation",
                    "value" : "<strong>Debug message</strong>\n<br/>\n{{formOutput._submitError.message}}\n{{submit_errors_list}}"
                  },
                  "alignment" : {
                    "type" : "constant",
                    "value" : "left"
                  },
                  "dimension" : {
                    "type" : "constant",
                    "value" : 12
                  }
                },
                "reference" : "1f27f5bd-524e-421e-a4c5-0215a57bf410",
                "hasValidationError" : false,
                "id" : "pbText",
                "description" : ""
              }
            ]
          ]
        }
      }
    ]
  ],
  "variables" : {
    "task" : {
      "type" : "url",
      "value" : [
        "../API/bpm/userTask/{{taskId}}"
      ],
      "exposed" : false
    },
    "formInput" : {
      "type" : "json",
      "value" : [
        "{\r",
        "  \"enviarEmail2\" : false\r",
        "}"
      ],
      "exposed" : false
    },
    "submit_errors_list" : {
      "type" : "expression",
      "value" : [
        "if($data.formOutput && $data.formOutput._submitError && $data.formOutput._submitError.explanations){",
        "\tconst liElements = $data.formOutput._submitError.explanations",
        "\t\t.filter(cause => cause !== null)",
        "\t\t.map(cause => \"<li>\" + cause + \"</li>\")",
        "\t\t.join('');",
        "\tif(liElements){",
        "\t\treturn \"<ul>\" + liElements + \"</ul>\";",
        "\t}",
        "}"
      ],
      "exposed" : false
    },
    "formOutput" : {
      "type" : "expression",
      "value" : [
        "return {",
        "\tenviarEmail2: $data.formInput.enviarEmail2",
        "}"
      ],
      "exposed" : false
    },
    "context" : {
      "type" : "url",
      "value" : [
        "../API/bpm/userTask/{{taskId}}/context"
      ],
      "exposed" : false
    },
    "taskId" : {
      "type" : "urlparameter",
      "value" : [
        "id"
      ],
      "exposed" : false
    }
  },
  "assets" : [
    {
      "id" : "fef65e73-2496-4dc0-8115-b854c551e18d",
      "name" : "style.css",
      "type" : "css",
      "order" : 0,
      "external" : false
    },
    {
      "id" : "2402d06c-4e14-460e-9b0d-be8d9584e612",
      "name" : "localization.json",
      "type" : "json",
      "order" : 0,
      "external" : false
    }
  ],
  "inactiveAssets" : [ ],
  "webResources" : [ ],
  "hasValidationError" : false
}